drhttp/__init__.py
drhttp/client.py
drhttp/defines.py
drhttp/middleware.py
drhttp/proxies.py
drhttp/utils.py
drhttp/wsgi.py
drhttp-0.2.0.dist-info/LICENSE
drhttp-0.2.0.dist-info/METADATA
drhttp-0.2.0.dist-info/WHEEL
drhttp-0.2.0.dist-info/top_level.txt
drhttp-0.2.0.dist-info/RECORD
