Metadata-Version: 2.1
Name: drhttp
Version: 0.2.0
Summary: Dr. Ashtetepe (drhttp) agent for python application servers
Home-page: https://drhttp.com/
Author: Pierre-Olivier Marec
Author-email: contact@drhttp.com
License: UNKNOWN
Platform: UNKNOWN
Classifier: Programming Language :: Python :: 3
Classifier: License :: OSI Approved :: GNU General Public License v3 (GPLv3)
Classifier: Operating System :: OS Independent
Requires-Dist: requests (==2.22.*)
